giv/__init__.py
giv/__main__.py
giv/cli.py
giv/commands/__init__.py
giv/commands/announcement.py
giv/commands/base.py
giv/commands/changelog.py
giv/commands/clear_cache.py
giv/commands/config.py
giv/commands/document.py
giv/commands/help.py
giv/commands/init.py
giv/commands/message.py
giv/commands/release_notes.py
giv/commands/summary.py
giv/commands/version.py
giv/config.py
giv/constants.py
giv/errors.py
giv/lib/__init__.py
giv/lib/git.py
giv/lib/llm.py
giv/lib/markdown.py
giv/lib/metadata.py
giv/lib/output.py
giv/lib/repository.py
giv/lib/summarization.py
giv/lib/templates.py
giv/lib/todo.py
giv/lib/utils.py
giv/main.py
giv/templates/announcement_prompt.md
giv/templates/changelog_prompt.md
giv/templates/commit_message_prompt.md
giv/templates/commit_summary_prompt.md
giv/templates/post_example.md
giv/templates/post_prompt.md
giv/templates/release_notes_prompt.md
giv/templates/summary_prompt.md
giv-0.6.0.dist-info/LICENSE
giv-0.6.0.dist-info/METADATA
giv-0.6.0.dist-info/WHEEL
giv-0.6.0.dist-info/entry_points.txt
giv-0.6.0.dist-info/RECORD
