Metadata-Version: 2.3
Name: giv
Version: 0.6.0
Summary: Intelligent Git commit message and changelog generator powered by AI
License: MIT
Keywords: git,commit,ai,changelog,cli,llm,openai
Author: fwdslsh
Author-email: fwdslshdev@gmail.com
Requires-Python: >=3.9.0,<3.14
Classifier: Development Status :: 5 - Production/Stable
Classifier: Environment :: Console
Classifier: Intended Audience :: Developers
Classifier: License :: OSI Approved :: MIT License
Classifier: Operating System :: OS Independent
Classifier: Programming Language :: Python :: 3
Classifier: Programming Language :: Python :: 3.9
Classifier: Programming Language :: Python :: 3.10
Classifier: Programming Language :: Python :: 3.11
Classifier: Programming Language :: Python :: 3.12
Classifier: Programming Language :: Python :: 3.13
Classifier: Topic :: Software Development :: Documentation
Classifier: Topic :: Software Development :: Version Control :: Git
Classifier: Topic :: Text Processing :: Markup :: Markdown
Requires-Dist: click (>=8.1.0,<9.0.0)
Requires-Dist: packaging (>=25.0,<26.0)
Requires-Dist: requests (>=2.31.0,<3.0.0)
Project-URL: Documentation, https://github.com/fwdslsh/giv/blob/main/README.md
Project-URL: Homepage, https://github.com/fwdslsh/giv
Project-URL: Repository, https://github.com/fwdslsh/giv
